xlstpl/__init__.py
xlstpl/richtexthandler.py
xlstpl/utils.py
xlstpl/writer.py
xlstpl/writerbase.py
xlstpl/xlext.py
xlstpl/xlnode.py
xlstpl/ynext.py
xlstpl-0.2.1.dist-info/LICENSE
xlstpl-0.2.1.dist-info/METADATA
xlstpl-0.2.1.dist-info/WHEEL
xlstpl-0.2.1.dist-info/top_level.txt
xlstpl-0.2.1.dist-info/RECORD
