Metadata-Version: 2.1
Name: xlstpl
Version: 0.2.1
Summary: A python module to generate xls files from a xls template
Home-page: https://github.com/zhangyu836/python-xls-template
Author: Zhang Yu
Author-email: zhangyu836@gmail.com
License: MIT
Keywords: xls,spreadsheet,workbook,template
Platform: Any platform 
Requires-Dist: xlrd
Requires-Dist: xlwt
Requires-Dist: openpyxl
Requires-Dist: jinja2
Requires-Dist: six
